probability/__init__.py
probability/probability.py
probability_tb-0.0.1.dist-info/LICENSE
probability_tb-0.0.1.dist-info/METADATA
probability_tb-0.0.1.dist-info/WHEEL
probability_tb-0.0.1.dist-info/top_level.txt
probability_tb-0.0.1.dist-info/RECORD
