Metadata-Version: 2.1
Name: probability_tb
Version: 0.0.1
Summary: A simple probability package which has a type probability
Author-email: Thomas Brumbaugh <thomas.william.brumbaugh@gmail.com>
Project-URL: Homepage, https://github.com/probability_tb
Project-URL: Issues, https://github.com/pypa/probability_tb/issues
Classifier: Programming Language :: Python :: 3
Classifier: License :: OSI Approved :: MIT License
Classifier: Operating System :: OS Independent
Requires-Python: >=3.8
License-File: LICENSE
